{"jmf_doc_generator_name": "Rohan", "_id": "client_1", "jmf_health_service_contractor": "Australia Health Care Pty Ltd", "insured_business_activity": "Network operator", "jmf_declaration_type": "MOTOR VEHICLE INSURANCE DECLARATION", "worker_compensation_insurer": "JLT", "insured_email": "insured@client.com", "jmf_client_address": "12, Times Square, New York, USA", "jmf_client_fax": "3211 1234", "insured_products": "Not advised", "jmf_client_license": "Proprietory", "jmf_client_telephone": "123456", "jmf_DateCreated": "07/12/2019", "worker_policy_number": "123", "insured_itc": "100%", "jmf_client_email": "client@client.com", "jmf_client_name": "Google", "insured_name": "John", "insured_contact": "9999999999", "insured_abn": "1234 1234"}